kotlin version: 2.0.21
error message: org.jetbrains.kotlin.codegen.CompilationException: Back-end (JVM) Internal error: Couldn't transform method node:
showPreDndNotification (Landroid/content/Context;Ljava/lang/String;Ljava/lang/Long;)V:
  @Landroid/annotation/SuppressLint;(value={"MissingPermission"}) // invisible
    // annotable parameter count: 3 (visible)
    // annotable parameter count: 3 (invisible)
    @Lorg/jetbrains/annotations/NotNull;() // invisible, parameter 0
    @Lorg/jetbrains/annotations/Nullable;() // invisible, parameter 1
    @Lorg/jetbrains/annotations/Nullable;() // invisible, parameter 2
    TRYCATCHBLOCK L0 L1 L2 java/lang/SecurityException
   L3
    ALOAD 1
    LDC "context"
    INVOKESTATIC kotlin/jvm/internal/Intrinsics.checkNotNullParameter (Ljava/lang/Object;Ljava/lang/String;)V
   L4
    LINENUMBER 31 L4
    GETSTATIC com/brunoafk/calendardnd/util/PermissionUtils.INSTANCE : Lcom/brunoafk/calendardnd/util/PermissionUtils;
    ALOAD 1
    INVOKEVIRTUAL com/brunoafk/calendardnd/util/PermissionUtils.hasNotificationPermission (Landroid/content/Context;)Z
    IFNE L5
   L6
    LINENUMBER 32 L6
    GETSTATIC kotlin/Unit.INSTANCE : Lkotlin/Unit;
    POP
    RETURN
   L7
    NOP
   L5
    LINENUMBER 35 L5
    ALOAD 0
    ALOAD 1
    INVOKESPECIAL com/brunoafk/calendardnd/system/notifications/DndNotificationHelper.ensureChannel (Landroid/content/Context;)V
   L8
    LINENUMBER 37 L8
    GETSTATIC com/brunoafk/calendardnd/util/LocaleUtils.INSTANCE : Lcom/brunoafk/calendardnd/util/LocaleUtils;
    ALOAD 1
    INVOKEVIRTUAL com/brunoafk/calendardnd/util/LocaleUtils.localizedContext (Landroid/content/Context;)Landroid/content/Context;
    ASTORE 4
   L9
    LINENUMBER 38 L9
    ALOAD 4
    GETSTATIC com/brunoafk/calendardnd/R$string.pre_dnd_notification_title : I
    INVOKEVIRTUAL android/content/Context.getString (I)Ljava/lang/String;
    ASTORE 6
   L10
    ALOAD 6
    LDC "getString(...)"
    INVOKESTATIC kotlin/jvm/internal/Intrinsics.checkNotNullExpressionValue (Ljava/lang/Object;Ljava/lang/String;)V
    ALOAD 6
   L11
    CHECKCAST java/lang/String
    ASTORE 5
   L12
    LINENUMBER 39 L12
    ALOAD 2
    CHECKCAST java/lang/CharSequence
    ASTORE 8
    NOP
   L13
    NOP
    ALOAD 8
    IFNULL L14
    ALOAD 8
    INVOKESTATIC kotlin/text/StringsKt.isBlank (Ljava/lang/CharSequence;)Z
    IFEQ L15
   L14
    ICONST_1
    GOTO L16
   L15
    ICONST_0
   L16
    NOP
    GOTO L17
   L17
    LINENUMBER 39 L17
    IFEQ L18
   L19
    LINENUMBER 40 L19
    ALOAD 4
    GETSTATIC com/brunoafk/calendardnd/R$string.pre_dnd_notification_body_generic : I
    INVOKEVIRTUAL android/content/Context.getString (I)Ljava/lang/String;
    GOTO L20
   L18
    LINENUMBER 42 L18
    ALOAD 4
    GETSTATIC com/brunoafk/calendardnd/R$string.pre_dnd_notification_body : I
    ICONST_1
    ANEWARRAY java/lang/Object
    ASTORE 8
   L21
    ALOAD 8
    ICONST_0
    ALOAD 2
    AASTORE
    ALOAD 8
   L22
    INVOKEVIRTUAL android/content/Context.getString (I[Ljava/lang/Object;)Ljava/lang/String;
   L20
    LINENUMBER 39 L20
    ASTORE 7
   L23
    ALOAD 7
    INVOKESTATIC kotlin/jvm/internal/Intrinsics.checkNotNull (Ljava/lang/Object;)V
    ALOAD 7
   L24
    CHECKCAST java/lang/String
    ASTORE 6
   L25
    LINENUMBER 45 L25
    NEW androidx/core/app/NotificationCompat$Builder
    DUP
    ALOAD 1
    LDC "dnd_reminders"
    INVOKESPECIAL androidx/core/app/NotificationCompat$Builder.<init> (Landroid/content/Context;Ljava/lang/String;)V
   L26
    LINENUMBER 46 L26
    GETSTATIC com/brunoafk/calendardnd/R$drawable.ic_notification : I
    INVOKEVIRTUAL androidx/core/app/NotificationCompat$Builder.setSmallIcon (I)Landroidx/core/app/NotificationCompat$Builder;
   L27
    LINENUMBER 47 L27
    ALOAD 5
    CHECKCAST java/lang/CharSequence
    INVOKEVIRTUAL androidx/core/app/NotificationCompat$Builder.setContentTitle (Ljava/lang/CharSequence;)Landroidx/core/app/NotificationCompat$Builder;
   L28
    LINENUMBER 48 L28
    ALOAD 6
    CHECKCAST java/lang/CharSequence
    INVOKEVIRTUAL androidx/core/app/NotificationCompat$Builder.setContentText (Ljava/lang/CharSequence;)Landroidx/core/app/NotificationCompat$Builder;
   L29
    LINENUMBER 49 L29
    NOP
    ICONST_1
    INVOKEVIRTUAL androidx/core/app/NotificationCompat$Builder.setAutoCancel (Z)Landroidx/core/app/NotificationCompat$Builder;
   L30
    LINENUMBER 50 L30
    ICONST_0
    INVOKEVIRTUAL androidx/core/app/NotificationCompat$Builder.setPriority (I)Landroidx/core/app/NotificationCompat$Builder;
    ASTORE 8
   L31
    ALOAD 8
    LDC "setPriority(...)"
    INVOKESTATIC kotlin/jvm/internal/Intrinsics.checkNotNullExpressionValue (Ljava/lang/Object;Ljava/lang/String;)V
    ALOAD 8
   L32
    CHECKCAST androidx/core/app/NotificationCompat$Builder
   L33
    LINENUMBER 45 L33
    ASTORE 7
   L34
    LINENUMBER 52 L34
    NEW android/content/Intent
    DUP
    ALOAD 1
    LDC Lcom/brunoafk/calendardnd/ui/MainActivity;.class
    CHECKCAST java/lang/Class
    INVOKESPECIAL android/content/Intent.<init> (Landroid/content/Context;Ljava/lang/Class;)V
    ASTORE 9
    NOP
   L35
    NOP
    ALOAD 9
    CHECKCAST android/content/Intent
    ASTORE 10
   L36
    ICONST_0
    ISTORE 11
   L37
    LINENUMBER 53 L37
    ALOAD 10
    LDC 335544320
    INVOKEVIRTUAL android/content/Intent.setFlags (I)Landroid/content/Intent;
    POP
   L38
    LINENUMBER 54 L38
    NOP
    GOTO L39
   L39
    GETSTATIC kotlin/Unit.INSTANCE : Lkotlin/Unit;
   L40
    LINENUMBER 52 L40
    POP
    ALOAD 9
    NOP
    GOTO L41
   L41
    LINENUMBER 52 L41
    CHECKCAST android/content/Intent
    ASTORE 8
   L42
    LINENUMBER 56 L42
    ALOAD 1
   L43
    LINENUMBER 57 L43
    ICONST_0
   L44
    LINENUMBER 58 L44
    ALOAD 8
   L45
    LINENUMBER 59 L45
    LDC 201326592
   L46
    LINENUMBER 55 L46
    INVOKESTATIC android/app/PendingIntent.getActivity (Landroid/content/Context;ILandroid/content/Intent;I)Landroid/app/PendingIntent;
    ASTORE 9
   L47
    LINENUMBER 61 L47
    ALOAD 7
    ALOAD 9
    INVOKEVIRTUAL androidx/core/app/NotificationCompat$Builder.setContentIntent (Landroid/app/PendingIntent;)Landroidx/core/app/NotificationCompat$Builder;
    POP
   L48
    LINENUMBER 63 L48
    ALOAD 3
    IFNULL L49
   L50
    LINENUMBER 64 L50
    NEW android/content/Intent
    DUP
    ALOAD 1
    LDC Lcom/brunoafk/calendardnd/system/receivers/EnableDndNowReceiver;.class
    CHECKCAST java/lang/Class
    INVOKESPECIAL android/content/Intent.<init> (Landroid/content/Context;Ljava/lang/Class;)V
    ASTORE 11
    NOP
   L51
    NOP
    ALOAD 11
    CHECKCAST android/content/Intent
    ASTORE 12
   L52
    ICONST_0
    ISTORE 13
   L53
    LINENUMBER 65 L53
    ALOAD 12
    LDC "com.brunoafk.calendardnd.action.ENABLE_DND_NOW"
    INVOKEVIRTUAL android/content/Intent.setAction (Ljava/lang/String;)Landroid/content/Intent;
    POP
   L54
    LINENUMBER 66 L54
    ALOAD 12
    LDC "extra_dnd_window_end_ms"
    ALOAD 3
    INVOKEVIRTUAL java/lang/Long.longValue ()J
    INVOKEVIRTUAL android/content/Intent.putExtra (Ljava/lang/String;J)Landroid/content/Intent;
    POP
   L55
    LINENUMBER 67 L55
    NOP
    GOTO L56
   L56
    GETSTATIC kotlin/Unit.INSTANCE : Lkotlin/Unit;
   L57
    LINENUMBER 64 L57
    POP
    ALOAD 11
    NOP
    GOTO L58
   L58
    LINENUMBER 64 L58
    CHECKCAST android/content/Intent
    ASTORE 10
   L59
    LINENUMBER 69 L59
    ALOAD 1
   L60
    LINENUMBER 70 L60
    ICONST_0
   L61
    LINENUMBER 71 L61
    ALOAD 10
   L62
    LINENUMBER 72 L62
    LDC 201326592
   L63
    LINENUMBER 68 L63
    INVOKESTATIC android/app/PendingIntent.getBroadcast (Landroid/content/Context;ILandroid/content/Intent;I)Landroid/app/PendingIntent;
    ASTORE 11
   L64
    LINENUMBER 74 L64
    ALOAD 7
   L65
    LINENUMBER 75 L65
    ICONST_0
   L66
    LINENUMBER 76 L66
    ALOAD 4
    GETSTATIC com/brunoafk/calendardnd/R$string.pre_dnd_notification_action : I
    INVOKEVIRTUAL android/content/Context.getString (I)Ljava/lang/String;
    CHECKCAST java/lang/CharSequence
   L67
    LINENUMBER 77 L67
    ALOAD 11
   L68
    LINENUMBER 74 L68
    INVOKEVIRTUAL androidx/core/app/NotificationCompat$Builder.addAction (ILjava/lang/CharSequence;Landroid/app/PendingIntent;)Landroidx/core/app/NotificationCompat$Builder;
   L69
    POP
   L49
    LINENUMBER 81 L49
    ALOAD 7
    INVOKEVIRTUAL androidx/core/app/NotificationCompat$Builder.build ()Landroid/app/Notification;
    ASTORE 11
   L70
    ALOAD 11
    LDC "build(...)"
    INVOKESTATIC kotlin/jvm/internal/Intrinsics.checkNotNullExpressionValue (Ljava/lang/Object;Ljava/lang/String;)V
    ALOAD 11
   L71
    CHECKCAST android/app/Notification
    ASTORE 10
   L72
    LINENUMBER 83 L72
    GETSTATIC com/brunoafk/calendardnd/util/AnalyticsTracker.INSTANCE : Lcom/brunoafk/calendardnd/util/AnalyticsTracker;
    ALOAD 1
    INVOKEVIRTUAL com/brunoafk/calendardnd/util/AnalyticsTracker.logPreDndNotificationShown (Landroid/content/Context;)V
   L73
    LINENUMBER 85 L73
   L74
   L0
    NOP
   L75
    LINENUMBER 86 L75
    ALOAD 1
    INVOKESTATIC androidx/core/app/NotificationManagerCompat.from (Landroid/content/Context;)Landroidx/core/app/NotificationManagerCompat;
    SIPUSH 2001
    ALOAD 10
    INVOKEVIRTUAL androidx/core/app/NotificationManagerCompat.notify (ILandroid/app/Notification;)V
   L1
    GOTO L76
   L2
    LINENUMBER 87 L2
    ASTORE 11
   L76
    LINENUMBER 90 L76
    NOP
    RETURN
   L77
    LOCALVARIABLE $i$a$-apply-DndNotificationHelper$showPreDndNotification$openIntent$1 I L37 L39 11
    LOCALVARIABLE $this$showPreDndNotification_u24lambda_u240 Landroid/content/Intent; L36 L39 10
    LOCALVARIABLE $i$a$-apply-DndNotificationHelper$showPreDndNotification$actionIntent$1 I L53 L56 13
    LOCALVARIABLE $this$showPreDndNotification_u24lambda_u241 Landroid/content/Intent; L52 L56 12
    LOCALVARIABLE actionIntent Landroid/content/Intent; L59 L69 10
    LOCALVARIABLE actionPendingIntent Landroid/app/PendingIntent; L64 L69 11
    LOCALVARIABLE e Ljava/lang/SecurityException; L76 L76 11
    LOCALVARIABLE stringsContext Landroid/content/Context; L9 L77 4
    LOCALVARIABLE title Ljava/lang/String; L12 L77 5
    LOCALVARIABLE text Ljava/lang/String; L25 L77 6
    LOCALVARIABLE builder Landroidx/core/app/NotificationCompat$Builder; L34 L77 7
    LOCALVARIABLE openIntent Landroid/content/Intent; L42 L77 8
    LOCALVARIABLE openPendingIntent Landroid/app/PendingIntent; L47 L77 9
    LOCALVARIABLE notification Landroid/app/Notification; L72 L77 10
    LOCALVARIABLE this Lcom/brunoafk/calendardnd/system/notifications/DndNotificationHelper; L3 L77 0
    LOCALVARIABLE context Landroid/content/Context; L3 L77 1
    LOCALVARIABLE meetingTitle Ljava/lang/String; L3 L77 2
    LOCALVARIABLE dndWindowEndMs Ljava/lang/Long; L3 L77 3
    MAXSTACK = 5
    MAXLOCALS = 14

File is unknown
The root cause java.lang.OutOfMemoryError was thrown at: org.jetbrains.kotlin.codegen.optimization.common.FastMethodAnalyzer._init_$lambda$0(FastMethodAnalyzer.kt:47)
	at org.jetbrains.kotlin.codegen.TransformationMethodVisitor.visitEnd(TransformationMethodVisitor.kt:89)
	at org.jetbrains.org.objectweb.asm.MethodVisitor.visitEnd(MethodVisitor.java:783)
	at org.jetbrains.org.objectweb.asm.tree.MethodNode.accept(MethodNode.java:772)
	at org.jetbrains.kotlin.backend.jvm.codegen.ClassCodegen.generateMethod(ClassCodegen.kt:453)
	at org.jetbrains.kotlin.backend.jvm.codegen.ClassCodegen.generate(ClassCodegen.kt:168)
	at org.jetbrains.kotlin.backend.jvm.FileCodegen.lower(JvmPhases.kt:39)
	at org.jetbrains.kotlin.backend.common.phaser.PhaseFactoriesKt.createFilePhase$lambda$4(PhaseFactories.kt:71)
	at org.jetbrains.kotlin.backend.common.phaser.PhaseBuildersKt$createSimpleNamedCompilerPhase$1.phaseBody(PhaseBuilders.kt:69)
	at org.jetbrains.kotlin.backend.common.phaser.SimpleNamedCompilerPhase.phaseBody(CompilerPhase.kt:226)
	at org.jetbrains.kotlin.backend.common.phaser.AbstractNamedCompilerPhase.invoke(CompilerPhase.kt:113)
	at org.jetbrains.kotlin.backend.common.phaser.PerformByIrFilePhase.invokeSequential(performByIrFile.kt:62)
	at org.jetbrains.kotlin.backend.common.phaser.PerformByIrFilePhase.invoke(performByIrFile.kt:52)
	at org.jetbrains.kotlin.backend.common.phaser.PerformByIrFilePhase.invoke(performByIrFile.kt:38)
	at org.jetbrains.kotlin.backend.common.phaser.NamedCompilerPhase.phaseBody(CompilerPhase.kt:166)
	at org.jetbrains.kotlin.backend.common.phaser.AbstractNamedCompilerPhase.invoke(CompilerPhase.kt:113)
	at org.jetbrains.kotlin.backend.common.phaser.CompositePhase.invoke(PhaseBuilders.kt:27)
	at org.jetbrains.kotlin.backend.common.phaser.CompositePhase.invoke(PhaseBuilders.kt:14)
	at org.jetbrains.kotlin.backend.common.phaser.NamedCompilerPhase.phaseBody(CompilerPhase.kt:166)
	at org.jetbrains.kotlin.backend.common.phaser.AbstractNamedCompilerPhase.invoke(CompilerPhase.kt:113)
	at org.jetbrains.kotlin.backend.common.phaser.CompilerPhaseKt.invokeToplevel(CompilerPhase.kt:62)
	at org.jetbrains.kotlin.backend.jvm.JvmIrCodegenFactory.invokeCodegen(JvmIrCodegenFactory.kt:371)
	at org.jetbrains.kotlin.codegen.CodegenFactory.generateModule(CodegenFactory.kt:47)
	at org.jetbrains.kotlin.backend.jvm.JvmIrCodegenFactory.generateModuleInFrontendIRMode(JvmIrCodegenFactory.kt:433)
	at org.jetbrains.kotlin.cli.jvm.compiler.pipeline.JvmCompilerPipelineKt.generateCodeFromIr(jvmCompilerPipeline.kt:246)
	at org.jetbrains.kotlin.cli.jvm.compiler.pipeline.JvmCompilerPipelineKt.compileModulesUsingFrontendIrAndLightTree(jvmCompilerPipeline.kt:142)
	at org.jetbrains.kotlin.cli.jvm.K2JVMCompiler.doExecute(K2JVMCompiler.kt:148)
	at org.jetbrains.kotlin.cli.jvm.K2JVMCompiler.doExecute(K2JVMCompiler.kt:43)
	at org.jetbrains.kotlin.cli.common.CLICompiler.execImpl(CLICompiler.kt:103)
	at org.jetbrains.kotlin.cli.common.CLICompiler.execImpl(CLICompiler.kt:49)
	at org.jetbrains.kotlin.cli.common.CLITool.exec(CLITool.kt:101)
	at org.jetbrains.kotlin.incremental.IncrementalJvmCompilerRunner.runCompiler(IncrementalJvmCompilerRunner.kt:464)
	at org.jetbrains.kotlin.incremental.IncrementalJvmCompilerRunner.runCompiler(IncrementalJvmCompilerRunner.kt:73)
	at org.jetbrains.kotlin.incremental.IncrementalCompilerRunner.doCompile(IncrementalCompilerRunner.kt:506)
	at org.jetbrains.kotlin.incremental.IncrementalCompilerRunner.compileImpl(IncrementalCompilerRunner.kt:423)
	at org.jetbrains.kotlin.incremental.IncrementalCompilerRunner.compileNonIncrementally(IncrementalCompilerRunner.kt:301)
	at org.jetbrains.kotlin.incremental.IncrementalCompilerRunner.compile(IncrementalCompilerRunner.kt:129)
	at org.jetbrains.kotlin.daemon.CompileServiceImplBase.execIncrementalCompiler(CompileServiceImpl.kt:675)
	at org.jetbrains.kotlin.daemon.CompileServiceImplBase.access$execIncrementalCompiler(CompileServiceImpl.kt:92)
	at org.jetbrains.kotlin.daemon.CompileServiceImpl.compile(CompileServiceImpl.kt:1660)
	at java.base/jdk.internal.reflect.NativeMethodAccessorImpl.invoke0(Native Method)
	at java.base/jdk.internal.reflect.NativeMethodAccessorImpl.invoke(NativeMethodAccessorImpl.java:77)
	at java.base/jdk.internal.reflect.DelegatingMethodAccessorImpl.invoke(DelegatingMethodAccessorImpl.java:43)
	at java.base/java.lang.reflect.Method.invoke(Method.java:569)
	at java.rmi/sun.rmi.server.UnicastServerRef.dispatch(UnicastServerRef.java:360)
	at java.rmi/sun.rmi.transport.Transport$1.run(Transport.java:200)
	at java.rmi/sun.rmi.transport.Transport$1.run(Transport.java:197)
	at java.base/java.security.AccessController.doPrivileged(AccessController.java:712)
	at java.rmi/sun.rmi.transport.Transport.serviceCall(Transport.java:196)
	at java.rmi/sun.rmi.transport.tcp.TCPTransport.handleMessages(TCPTransport.java:587)
	at java.rmi/sun.rmi.transport.tcp.TCPTransport$ConnectionHandler.run0(TCPTransport.java:828)
	at java.rmi/sun.rmi.transport.tcp.TCPTransport$ConnectionHandler.lambda$run$0(TCPTransport.java:705)
	at java.base/java.security.AccessController.doPrivileged(AccessController.java:399)
	at java.rmi/sun.rmi.transport.tcp.TCPTransport$ConnectionHandler.run(TCPTransport.java:704)
	at java.base/java.util.concurrent.ThreadPoolExecutor.runWorker(ThreadPoolExecutor.java:1136)
	at java.base/java.util.concurrent.ThreadPoolExecutor$Worker.run(ThreadPoolExecutor.java:635)
	at java.base/java.lang.Thread.run(Thread.java:840)
Caused by: java.lang.OutOfMemoryError: GC overhead limit exceeded
	at org.jetbrains.kotlin.codegen.optimization.common.FastMethodAnalyzer._init_$lambda$0(FastMethodAnalyzer.kt:47)
	at org.jetbrains.kotlin.codegen.optimization.common.FastMethodAnalyzer$$Lambda$3343/0x000000d801b3e1b0.invoke(Unknown Source)
	at org.jetbrains.kotlin.codegen.optimization.common.FastAnalyzer.fullMergeControlFlowEdge(FastAnalyzer.kt:233)
	at org.jetbrains.kotlin.codegen.optimization.common.FastAnalyzer.mergeControlFlowEdge(FastAnalyzer.kt:216)
	at org.jetbrains.kotlin.codegen.optimization.common.FastAnalyzer.processControlFlowEdge(FastAnalyzer.kt:208)
	at org.jetbrains.kotlin.codegen.optimization.common.FastAnalyzer.processControlFlowEdge$default(FastAnalyzer.kt:206)
	at org.jetbrains.kotlin.codegen.optimization.common.FastAnalyzer.visitJumpInsnNode(FastAnalyzer.kt:318)
	at org.jetbrains.kotlin.codegen.optimization.common.FastAnalyzer.visitMeaningfulInstruction(FastAnalyzer.kt:275)
	at org.jetbrains.kotlin.codegen.optimization.common.FastAnalyzer.analyzeInstruction(FastAnalyzer.kt:113)
	at org.jetbrains.kotlin.codegen.optimization.common.FastAnalyzer.analyzeMainLoop(FastAnalyzer.kt:74)
	at org.jetbrains.kotlin.codegen.optimization.common.FastAnalyzer.analyze(FastAnalyzer.kt:53)
	at org.jetbrains.kotlin.codegen.optimization.RedundantCheckCastEliminationMethodTransformer.transform(RedundantCheckCastElimination.kt:54)
	at org.jetbrains.kotlin.codegen.optimization.transformer.CompositeMethodTransformer.transform(CompositeMethodTransformer.kt:25)
	at org.jetbrains.kotlin.codegen.optimization.OptimizationMethodVisitor.performTransformations(OptimizationMethodVisitor.kt:74)
	at org.jetbrains.kotlin.codegen.TransformationMethodVisitor.visitEnd(TransformationMethodVisitor.kt:67)
	at org.jetbrains.org.objectweb.asm.MethodVisitor.visitEnd(MethodVisitor.java:783)
	at org.jetbrains.org.objectweb.asm.tree.MethodNode.accept(MethodNode.java:772)
	at org.jetbrains.kotlin.backend.jvm.codegen.ClassCodegen.generateMethod(ClassCodegen.kt:453)
	at org.jetbrains.kotlin.backend.jvm.codegen.ClassCodegen.generate(ClassCodegen.kt:168)
	at org.jetbrains.kotlin.backend.jvm.FileCodegen.lower(JvmPhases.kt:39)
	at org.jetbrains.kotlin.backend.common.phaser.PhaseFactoriesKt.createFilePhase$lambda$4(PhaseFactories.kt:71)
	at org.jetbrains.kotlin.backend.common.phaser.PhaseFactoriesKt$$Lambda$203/0x000000d80114ef18.invoke(Unknown Source)
	at org.jetbrains.kotlin.backend.common.phaser.PhaseBuildersKt$createSimpleNamedCompilerPhase$1.phaseBody(PhaseBuilders.kt:69)
	at org.jetbrains.kotlin.backend.common.phaser.SimpleNamedCompilerPhase.phaseBody(CompilerPhase.kt:226)
	at org.jetbrains.kotlin.backend.common.phaser.AbstractNamedCompilerPhase.invoke(CompilerPhase.kt:113)
	at org.jetbrains.kotlin.backend.common.phaser.PerformByIrFilePhase.invokeSequential(performByIrFile.kt:62)
	at org.jetbrains.kotlin.backend.common.phaser.PerformByIrFilePhase.invoke(performByIrFile.kt:52)
	at org.jetbrains.kotlin.backend.common.phaser.PerformByIrFilePhase.invoke(performByIrFile.kt:38)
	at org.jetbrains.kotlin.backend.common.phaser.NamedCompilerPhase.phaseBody(CompilerPhase.kt:166)
	at org.jetbrains.kotlin.backend.common.phaser.AbstractNamedCompilerPhase.invoke(CompilerPhase.kt:113)
	at org.jetbrains.kotlin.backend.common.phaser.CompositePhase.invoke(PhaseBuilders.kt:27)
	at org.jetbrains.kotlin.backend.common.phaser.CompositePhase.invoke(PhaseBuilders.kt:14)


